mypackage/__init__.py
publish_pypi_setup-0.0.1.dist-info/LICENSE
publish_pypi_setup-0.0.1.dist-info/METADATA
publish_pypi_setup-0.0.1.dist-info/WHEEL
publish_pypi_setup-0.0.1.dist-info/top_level.txt
publish_pypi_setup-0.0.1.dist-info/RECORD
